esrgan.py
esrgan_client.py
esrgan_cli-1.1.2.dist-info/LICENSE
esrgan_cli-1.1.2.dist-info/METADATA
esrgan_cli-1.1.2.dist-info/WHEEL
esrgan_cli-1.1.2.dist-info/entry_points.txt
esrgan_cli-1.1.2.dist-info/top_level.txt
esrgan_cli-1.1.2.dist-info/RECORD
